pytomlcleaner/__init__.py
pytomlcleaner/cleaner.py
pytomlcleaner/cli.py
pytomlcleaner-1.0.0.dist-info/licenses/LICENSE
pytomlcleaner-1.0.0.dist-info/METADATA
pytomlcleaner-1.0.0.dist-info/WHEEL
pytomlcleaner-1.0.0.dist-info/entry_points.txt
pytomlcleaner-1.0.0.dist-info/top_level.txt
pytomlcleaner-1.0.0.dist-info/RECORD
