Metadata-Version: 2.4
Name: pytomlcleaner
Version: 1.0.0
Summary: A utility to find and remove unused dependencies in pyproject.toml.
Author: Thien Tran
License: Apache-2.0
Keywords: toml,dependencies,cleanup,pyproject
Requires-Python: >=3.9
License-File: LICENSE
Requires-Dist: tomlkit>=0.12.0
Requires-Dist: tomli>=2.0.1; python_version < "3.11"
Requires-Dist: stdlib-list>=0.10.0
Requires-Dist: black>=25.11.0
Requires-Dist: mypy>=1.19.1
Provides-Extra: dev
Requires-Dist: mypy>=1.8.0; extra == "dev"
Requires-Dist: pytest>=7.4.0; extra == "dev"
Dynamic: license-file
